{
  "configVersion": 1,
  "timestamp": 1669111643134,
  "index": "https://dcp.f80lab.com/index.html",
  "assetGroups": [
    {
      "name": "app",
      "installMode": "prefetch",
      "updateMode": "prefetch",
      "cacheQueryOptions": {
        "ignoreVary": true
      },
      "urls": [
        "https://dcp.f80lab.com/971.js",
        "https://dcp.f80lab.com/favicon.ico",
        "https://dcp.f80lab.com/index.html",
        "https://dcp.f80lab.com/main.js",
        "https://dcp.f80lab.com/manifest.webmanifest",
        "https://dcp.f80lab.com/polyfills.js",
        "https://dcp.f80lab.com/runtime.js",
        "https://dcp.f80lab.com/styles.css"
      ],
      "patterns": []
    },
    {
      "name": "assets",
      "installMode": "lazy",
      "updateMode": "prefetch",
      "cacheQueryOptions": {
        "ignoreVary": true
      },
      "urls": [
        "https://dcp.f80lab.com/assets/Reporting.xlsx",
        "https://dcp.f80lab.com/assets/Reporting_local.xlsx",
        "https://dcp.f80lab.com/assets/add_black_24dp.svg",
        "https://dcp.f80lab.com/assets/add_circle_outline_black_24dp.svg",
        "https://dcp.f80lab.com/assets/arrow_back_ios_black_24dp.svg",
        "https://dcp.f80lab.com/assets/arrow_forward_ios_black_24dp.svg",
        "https://dcp.f80lab.com/assets/article_black_24dp.svg",
        "https://dcp.f80lab.com/assets/cancel_black_24dp.svg",
        "https://dcp.f80lab.com/assets/close_black_24dp.svg",
        "https://dcp.f80lab.com/assets/default_jobs.json",
        "https://dcp.f80lab.com/assets/east_black_24dp.svg",
        "https://dcp.f80lab.com/assets/help_black_24dp.svg",
        "https://dcp.f80lab.com/assets/icons/LinkedIn.png",
        "https://dcp.f80lab.com/assets/icons/icon-128x128.png",
        "https://dcp.f80lab.com/assets/icons/icon-144x144.png",
        "https://dcp.f80lab.com/assets/icons/icon-152x152.png",
        "https://dcp.f80lab.com/assets/icons/icon-192x192.png",
        "https://dcp.f80lab.com/assets/icons/icon-384x384.png",
        "https://dcp.f80lab.com/assets/icons/icon-512x512.png",
        "https://dcp.f80lab.com/assets/icons/icon-72x72.png",
        "https://dcp.f80lab.com/assets/icons/icon-96x96.png",
        "https://dcp.f80lab.com/assets/img/anciens.jpg",
        "https://dcp.f80lab.com/assets/img/anonymous.png",
        "https://dcp.f80lab.com/assets/img/boy.png",
        "https://dcp.f80lab.com/assets/img/cercle_blanc.png",
        "https://dcp.f80lab.com/assets/img/charts.jpeg",
        "https://dcp.f80lab.com/assets/img/extrude.png",
        "https://dcp.f80lab.com/assets/img/gears.gif",
        "https://dcp.f80lab.com/assets/img/girl.png",
        "https://dcp.f80lab.com/assets/img/hammer_1f528.png",
        "https://dcp.f80lab.com/assets/img/lafemis.jpg",
        "https://dcp.f80lab.com/assets/img/movie.png",
        "https://dcp.f80lab.com/assets/img/movies.jpeg",
        "https://dcp.f80lab.com/assets/img/tips.png",
        "https://dcp.f80lab.com/assets/info_black_24dp.svg",
        "https://dcp.f80lab.com/assets/jobs.json",
        "https://dcp.f80lab.com/assets/jobs_old.json",
        "https://dcp.f80lab.com/assets/keyboard_arrow_down_black_24dp.svg",
        "https://dcp.f80lab.com/assets/login_black_24dp.svg",
        "https://dcp.f80lab.com/assets/logo_femis_intro.png",
        "https://dcp.f80lab.com/assets/logo_femis_intro@2x.png",
        "https://dcp.f80lab.com/assets/logo_femis_menu@2x.png",
        "https://dcp.f80lab.com/assets/logo_femis_menu@2x@2x.png",
        "https://dcp.f80lab.com/assets/logo_intro.png",
        "https://dcp.f80lab.com/assets/logo_intro@2x.png",
        "https://dcp.f80lab.com/assets/logo_menu.png",
        "https://dcp.f80lab.com/assets/logo_menu@2x.png",
        "https://dcp.f80lab.com/assets/logout_black_24dp.svg",
        "https://dcp.f80lab.com/assets/menu_black_24dp.svg",
        "https://dcp.f80lab.com/assets/menu_open_black_24dp.svg",
        "https://dcp.f80lab.com/assets/movie_filter_black_24dp.svg",
        "https://dcp.f80lab.com/assets/noun-award-1199466.svg",
        "https://dcp.f80lab.com/assets/noun-award-2825177.svg",
        "https://dcp.f80lab.com/assets/noun-clapperboard-1568085.svg",
        "https://dcp.f80lab.com/assets/noun-directories-1131457.svg",
        "https://dcp.f80lab.com/assets/noun-link-1880307.svg",
        "https://dcp.f80lab.com/assets/noun-masks-1595665.svg",
        "https://dcp.f80lab.com/assets/noun-movie-5241185.svg",
        "https://dcp.f80lab.com/assets/noun-trophy-2670394.svg",
        "https://dcp.f80lab.com/assets/noun-trophy-4503413.svg",
        "https://dcp.f80lab.com/assets/people_black_24dp.svg",
        "https://dcp.f80lab.com/assets/question_mark_black_24dp.svg",
        "https://dcp.f80lab.com/assets/reply_black_24dp.svg",
        "https://dcp.f80lab.com/assets/reporting.pbix",
        "https://dcp.f80lab.com/assets/rss_feed_black_24dp.svg",
        "https://dcp.f80lab.com/assets/search_black_24dp.svg",
        "https://dcp.f80lab.com/assets/share_black_24dp.svg",
        "https://dcp.f80lab.com/assets/theaters_black_24dp.svg",
        "https://dcp.f80lab.com/assets/visibility_black_24dp.svg"
      ],
      "patterns": []
    }
  ],
  "dataGroups": [
    {
      "name": "static",
      "patterns": [
        "\\/assets\\/i18n\\/.*"
      ],
      "strategy": "performance",
      "maxSize": 500,
      "maxAge": 259200000,
      "cacheQueryOptions": {
        "ignoreVary": true
      },
      "version": 1
    },
    {
      "name": "api-perf",
      "patterns": [
        "\\/api\\/profilsdoc\\/.*"
      ],
      "strategy": "performance",
      "maxSize": 5000,
      "maxAge": 3600000,
      "timeoutMs": 50000,
      "cacheQueryOptions": {
        "ignoreVary": true
      },
      "version": 1
    },
    {
      "name": "api-freshness",
      "patterns": [
        "\\/api-token-auth\\/"
      ],
      "strategy": "freshness",
      "maxSize": 100,
      "maxAge": 259200000,
      "timeoutMs": 10000,
      "cacheQueryOptions": {
        "ignoreVary": true
      },
      "version": 1
    }
  ],
  "hashTable": {
    "https://dcp.f80lab.com/971.js": "7554a5c72b2f08cc97a49f57768b89e72bbc83cc",
    "https://dcp.f80lab.com/assets/Reporting.xlsx": "c1c0d06e32155034ed44631082191f125f0cd8d5",
    "https://dcp.f80lab.com/assets/Reporting_local.xlsx": "3eeea79914897a86ec1e96881b63cb4ae3613a14",
    "https://dcp.f80lab.com/assets/add_black_24dp.svg": "11995169007069a036e8ff5b20176954fe56d26c",
    "https://dcp.f80lab.com/assets/add_circle_outline_black_24dp.svg": "fa8cf4d4c976a35b490d6ea51cc86532b1a51a05",
    "https://dcp.f80lab.com/assets/arrow_back_ios_black_24dp.svg": "32410d558d0c9e801cd3febc79d05837fe10fff2",
    "https://dcp.f80lab.com/assets/arrow_forward_ios_black_24dp.svg": "e9c5a911ad5667b1f550a92201f1d2b50cef0b60",
    "https://dcp.f80lab.com/assets/article_black_24dp.svg": "07547bd0a46075c4cf388dcb5c1411bb155d47d4",
    "https://dcp.f80lab.com/assets/cancel_black_24dp.svg": "1c143045389697469cc8b16d06a344718306debf",
    "https://dcp.f80lab.com/assets/close_black_24dp.svg": "8238a1bcdf6706703fcb6d4efaf36c3f19c47d0f",
    "https://dcp.f80lab.com/assets/default_jobs.json": "2c564458c2e15d101fadf154cbb3171407ed39c2",
    "https://dcp.f80lab.com/assets/east_black_24dp.svg": "e1983302a3512f8ff8a3ba527912a77ec11a7f49",
    "https://dcp.f80lab.com/assets/help_black_24dp.svg": "9b9fc05d6884ec01702adfe65f293812c52078a0",
    "https://dcp.f80lab.com/assets/icons/LinkedIn.png": "dec770e0a226b15021d0b80154aa18841097a46e",
    "https://dcp.f80lab.com/assets/icons/icon-128x128.png": "e4d97b0610bd65a82f10edfccd160ed449d51579",
    "https://dcp.f80lab.com/assets/icons/icon-144x144.png": "9f7bd0172af271f104989cd35c8e86b3600b15a7",
    "https://dcp.f80lab.com/assets/icons/icon-152x152.png": "07ac90d872d1f10d30810acab70ac86a1c5d2d44",
    "https://dcp.f80lab.com/assets/icons/icon-192x192.png": "a476503d5585bc48dd0e919f01c98d5b02b24672",
    "https://dcp.f80lab.com/assets/icons/icon-384x384.png": "d263cc629af9363828a5ef029708d2b377ee4190",
    "https://dcp.f80lab.com/assets/icons/icon-512x512.png": "2ebaa5b628a34ea892890d8e84687194ae3a6666",
    "https://dcp.f80lab.com/assets/icons/icon-72x72.png": "5ed7cef36e6adeae1ecbc86b90bf03e526e5c365",
    "https://dcp.f80lab.com/assets/icons/icon-96x96.png": "9b7e46d888bd8e68cfe45664bbcb1f4abd2de548",
    "https://dcp.f80lab.com/assets/img/anciens.jpg": "fd10c1fa0c85a0800a0f040ce57baeadaf0d551e",
    "https://dcp.f80lab.com/assets/img/anonymous.png": "1d7939f7ed357fb35d213cf4ff50ea144d0e6be3",
    "https://dcp.f80lab.com/assets/img/boy.png": "ee167f07e0b191e1fd7515d414ebe17df1bffc7c",
    "https://dcp.f80lab.com/assets/img/cercle_blanc.png": "9a6303385a785ed3fe3071aa06e5c7f66f14e074",
    "https://dcp.f80lab.com/assets/img/charts.jpeg": "f005d708eba10115db8b242eab30950f880db6ce",
    "https://dcp.f80lab.com/assets/img/extrude.png": "c6b705e0f3b620c451db7ad9c05ff34c8b474cb8",
    "https://dcp.f80lab.com/assets/img/gears.gif": "bc355afcdcd7c1ab2a1018257b35f10df37c829f",
    "https://dcp.f80lab.com/assets/img/girl.png": "e8c9f6fc5e44cff0732e4abbc43990102b2b1ad9",
    "https://dcp.f80lab.com/assets/img/hammer_1f528.png": "4df35a3abee020df341a816929f5d7b807ec8352",
    "https://dcp.f80lab.com/assets/img/lafemis.jpg": "0116e246057b5ffa42c637cf4016f6ad610474ab",
    "https://dcp.f80lab.com/assets/img/movie.png": "a09876c97c4f4abd0e31c455207818e7f758ba49",
    "https://dcp.f80lab.com/assets/img/movies.jpeg": "705d4c6567dd0455c51cc9318dabdd68a247aebd",
    "https://dcp.f80lab.com/assets/img/tips.png": "b7832ac8a831f94cd9b656f48bc0d75a5cd587ca",
    "https://dcp.f80lab.com/assets/info_black_24dp.svg": "cdf58b833a082d21deeb9a04bbfc30c36a51744a",
    "https://dcp.f80lab.com/assets/jobs.json": "e6e9d50780d2f6381fddf00f26635b5c9d285bbe",
    "https://dcp.f80lab.com/assets/jobs_old.json": "e6e9d50780d2f6381fddf00f26635b5c9d285bbe",
    "https://dcp.f80lab.com/assets/keyboard_arrow_down_black_24dp.svg": "dd857084fb036b8279feabf565d2a983e30a4d26",
    "https://dcp.f80lab.com/assets/login_black_24dp.svg": "4f50c6d31baab885e9d597b5c3314c14a5bfe199",
    "https://dcp.f80lab.com/assets/logo_femis_intro.png": "659475277094a5d5fe790d88f91fb22fc0e5fbe4",
    "https://dcp.f80lab.com/assets/logo_femis_intro@2x.png": "924f462bc7e8788bbefef7020d5f2b4bee27ada3",
    "https://dcp.f80lab.com/assets/logo_femis_menu@2x.png": "9747e3bf98f3f154cd862daf522d4fee91d0daf7",
    "https://dcp.f80lab.com/assets/logo_femis_menu@2x@2x.png": "6226612d477df2443cac875629da23e7ebf301fb",
    "https://dcp.f80lab.com/assets/logo_intro.png": "9fe48c7cc1175b4fcc491ca23e33f5df83f05b31",
    "https://dcp.f80lab.com/assets/logo_intro@2x.png": "e6c4bdf138226bf5b65450e5f982adf038e5e2cf",
    "https://dcp.f80lab.com/assets/logo_menu.png": "02b3cc3107761208ebcf4623c3ba2232f8e38e83",
    "https://dcp.f80lab.com/assets/logo_menu@2x.png": "f26fe06a31ff2f576e9fbd9d0adca20da3ff74b3",
    "https://dcp.f80lab.com/assets/logout_black_24dp.svg": "2ca3e67fb32c43423dabaa9ca507db6bd94c652c",
    "https://dcp.f80lab.com/assets/menu_black_24dp.svg": "69bcd9def97fbb56ecea63d9eead2ab6fcad7d04",
    "https://dcp.f80lab.com/assets/menu_open_black_24dp.svg": "5853b0f5098fdf9ab369c18dc3bfdfdac39e404e",
    "https://dcp.f80lab.com/assets/movie_filter_black_24dp.svg": "651ff8c75edc713e2de6d93186e76e6e35c43746",
    "https://dcp.f80lab.com/assets/noun-award-1199466.svg": "e05cd684555875742e7bbc517b5bebd93264b4c9",
    "https://dcp.f80lab.com/assets/noun-award-2825177.svg": "d7434f985a3711c60b52d56ffdbadddc7365c061",
    "https://dcp.f80lab.com/assets/noun-clapperboard-1568085.svg": "0a869137779e0d6b34579517f39d5286cc796bf5",
    "https://dcp.f80lab.com/assets/noun-directories-1131457.svg": "3e21315f516425f62e38d4b8161f3e4eb33c387a",
    "https://dcp.f80lab.com/assets/noun-link-1880307.svg": "61514ac4d29873613e345622f924724387ecca65",
    "https://dcp.f80lab.com/assets/noun-masks-1595665.svg": "764c32486f77eed644194997013bc3351a3223dc",
    "https://dcp.f80lab.com/assets/noun-movie-5241185.svg": "772344e04b9785c4bd3048996dbc6e521e41df8b",
    "https://dcp.f80lab.com/assets/noun-trophy-2670394.svg": "42f8da5145b208ee597e8b1f7df92db0c913c79d",
    "https://dcp.f80lab.com/assets/noun-trophy-4503413.svg": "d0f5ba7e13d6d4e01c8436851445d480abed3c34",
    "https://dcp.f80lab.com/assets/people_black_24dp.svg": "3fa10b71b416d17d54a6c7d15a29a15d9291058d",
    "https://dcp.f80lab.com/assets/question_mark_black_24dp.svg": "e55c5e937158452b18f1c00597e50338987117ec",
    "https://dcp.f80lab.com/assets/reply_black_24dp.svg": "0b8ff5af244298f295dd2fe2d8803231467e1ade",
    "https://dcp.f80lab.com/assets/reporting.pbix": "2b95ac35c6fee4fa408666be84d70943d4604ae8",
    "https://dcp.f80lab.com/assets/rss_feed_black_24dp.svg": "493c39b190dfae43c5dbee0b85b62285f7c49ec5",
    "https://dcp.f80lab.com/assets/search_black_24dp.svg": "5c7fded8e3ac1c20f8fe5f675cece05c6308d10a",
    "https://dcp.f80lab.com/assets/share_black_24dp.svg": "adfdac62c43beb15aa2f5645432a57d71bc41a01",
    "https://dcp.f80lab.com/assets/theaters_black_24dp.svg": "fc393acb8b1c5fbadb03ae3e30598ef1b300253d",
    "https://dcp.f80lab.com/assets/visibility_black_24dp.svg": "a73738806afd9c018cc55b88dbc181d2bfea49c6",
    "https://dcp.f80lab.com/favicon.ico": "ac6b2455e4fb868e4013fa4acf6de0aba0dda933",
    "https://dcp.f80lab.com/index.html": "b622aacaf351a5dc609ba4a6d52aa3c6455cd7d5",
    "https://dcp.f80lab.com/main.js": "11a1b86e9fe930bdee476a5c45d09ac636806582",
    "https://dcp.f80lab.com/manifest.webmanifest": "5430bb03fa346e338146a0956939e110243e7d40",
    "https://dcp.f80lab.com/polyfills.js": "8d78b26ae53508c93a7bb6e40d0150de7a02fcb2",
    "https://dcp.f80lab.com/runtime.js": "82a1a0422e19bb4fe82d2fb96ae78add9e44e453",
    "https://dcp.f80lab.com/styles.css": "3fad6d5db184600e1938a689b10226aa1b4b5fd5"
  },
  "navigationUrls": [
    {
      "positive": true,
      "regex": "^\\/.*$"
    },
    {
      "positive": false,
      "regex": "^\\/(?:.+\\/)?[^/]*\\.[^/]*$"
    },
    {
      "positive": false,
      "regex": "^\\/(?:.+\\/)?[^/]*__[^/]*$"
    },
    {
      "positive": false,
      "regex": "^\\/(?:.+\\/)?[^/]*__[^/]*\\/.*$"
    }
  ],
  "navigationRequestStrategy": "performance"
}